_vovp.cpython-38-x86_64-linux-gnu.so
vovp/__init__.py
vovp/client.py
vovp/multiprocessing.py
vovp_lib/libarrow.so.300
vovp_lib/libplasma_client.so
vovp_lib/plasma-store-server
vovp-0.0.2.dist-info/LICENSE
vovp-0.0.2.dist-info/METADATA
vovp-0.0.2.dist-info/WHEEL
vovp-0.0.2.dist-info/top_level.txt
vovp-0.0.2.dist-info/RECORD
