Metadata-Version: 2.1
Name: vovp
Version: 0.0.2
Summary: A test project using pybind11 and CMake
Home-page: UNKNOWN
Author: Dean Moldovan
Author-email: dean0x7d@gmail.com
License: UNKNOWN
Platform: UNKNOWN
